setup.py
dist_prob_binomial_gaussian/Binomialdistribution.py
dist_prob_binomial_gaussian/Gaussiandistribution.py
dist_prob_binomial_gaussian/Generaldistribution.py
dist_prob_binomial_gaussian/__init__.py
dist_prob_binomial_gaussian.egg-info/PKG-INFO
dist_prob_binomial_gaussian.egg-info/SOURCES.txt
dist_prob_binomial_gaussian.egg-info/dependency_links.txt
dist_prob_binomial_gaussian.egg-info/not-zip-safe
dist_prob_binomial_gaussian.egg-info/top_level.txt