Metadata-Version: 1.0
Name: dist-prob-binomial-gaussian
Version: 0.1
Summary: Binomial and Gaussian distributions
Home-page: UNKNOWN
Author: Abhishek Kumar Singh
Author-email: abhishek.kumar.singh2101@gmail.com
License: UNKNOWN
Platform: UNKNOWN
